odoo/addons/website_sale_suggest_create_account/README.rst
odoo/addons/website_sale_suggest_create_account/__init__.py
odoo/addons/website_sale_suggest_create_account/__manifest__.py
odoo/addons/website_sale_suggest_create_account/hooks.py
odoo/addons/website_sale_suggest_create_account/i18n/ca.po
odoo/addons/website_sale_suggest_create_account/i18n/ca_ES.po
odoo/addons/website_sale_suggest_create_account/i18n/de.po
odoo/addons/website_sale_suggest_create_account/i18n/es.po
odoo/addons/website_sale_suggest_create_account/i18n/es_CO.po
odoo/addons/website_sale_suggest_create_account/i18n/es_VE.po
odoo/addons/website_sale_suggest_create_account/i18n/fr.po
odoo/addons/website_sale_suggest_create_account/i18n/hr.po
odoo/addons/website_sale_suggest_create_account/i18n/it.po
odoo/addons/website_sale_suggest_create_account/i18n/nl.po
odoo/addons/website_sale_suggest_create_account/i18n/pt_BR.po
odoo/addons/website_sale_suggest_create_account/i18n/sl.po
odoo/addons/website_sale_suggest_create_account/i18n/website_sale_suggest_create_account.pot
odoo/addons/website_sale_suggest_create_account/readme/CONTRIBUTORS.md
odoo/addons/website_sale_suggest_create_account/readme/DESCRIPTION.md
odoo/addons/website_sale_suggest_create_account/readme/USAGE.md
odoo/addons/website_sale_suggest_create_account/static/description/icon.png
odoo/addons/website_sale_suggest_create_account/static/description/index.html
odoo/addons/website_sale_suggest_create_account/static/tests/tours/checkout.esm.js
odoo/addons/website_sale_suggest_create_account/tests/__init__.py
odoo/addons/website_sale_suggest_create_account/tests/test_shop_buy.py
odoo/addons/website_sale_suggest_create_account/views/website_sale.xml
odoo_addon_website_sale_suggest_create_account-18.0.1.0.0.3.dist-info/METADATA
odoo_addon_website_sale_suggest_create_account-18.0.1.0.0.3.dist-info/WHEEL
odoo_addon_website_sale_suggest_create_account-18.0.1.0.0.3.dist-info/top_level.txt
odoo_addon_website_sale_suggest_create_account-18.0.1.0.0.3.dist-info/RECORD
