Metadata-Version: 2.1
Name: odoo-addon-website_sale_suggest_create_account
Version: 18.0.1.0.0.3
Requires-Python: >=3.10
Requires-Dist: odoo==18.0.*
Summary: Suggest users to create an account when buying in the website
Home-page: https://github.com/OCA/e-commerce
License: LGPL-3
Author: Tecnativa, LasLabs, Odoo Community Association (OCA)
Author-email: support@odoo-community.org
Classifier: Programming Language :: Python
Classifier: Framework :: Odoo
Classifier: Framework :: Odoo :: 18.0
Classifier: License :: OSI Approved :: GNU Lesser General Public License v3 (LGPLv3)
